LiexinWuyajiushu/README.md
LiexinWuyajiushu/__init__.py
LiexinWuyajiushu/__main__.py
LiexinWuyajiushu/file.epub
LiexinWuyajiushu/index.html
LiexinWuyajiushu/css/__init__.py
LiexinWuyajiushu/css/annotations.css
LiexinWuyajiushu/css/main.css
LiexinWuyajiushu/css/normalize.css
LiexinWuyajiushu/css/popup.css
LiexinWuyajiushu/font/__init__.py
LiexinWuyajiushu/font/fontello.eot
LiexinWuyajiushu/font/fontello.svg
LiexinWuyajiushu/font/fontello.ttf
LiexinWuyajiushu/font/fontello.woff
LiexinWuyajiushu/img/__init__.py
LiexinWuyajiushu/img/annotator-glyph-sprite.png
LiexinWuyajiushu/img/annotator-icon-sprite.png
LiexinWuyajiushu/img/apple-touch-icon.png
LiexinWuyajiushu/img/cancelfullscreen.png
LiexinWuyajiushu/img/close.png
LiexinWuyajiushu/img/fullscreen.png
LiexinWuyajiushu/img/loader.gif
LiexinWuyajiushu/img/menu-icon.png
LiexinWuyajiushu/img/save.png
LiexinWuyajiushu/img/saved.png
LiexinWuyajiushu/img/settings-s.png
LiexinWuyajiushu/img/settings.png
LiexinWuyajiushu/img/star.png
LiexinWuyajiushu/js/__init__.py
LiexinWuyajiushu/js/epub.js
LiexinWuyajiushu/js/epub.min.js
LiexinWuyajiushu/js/epub.min.map
LiexinWuyajiushu/js/hooks.min.js
LiexinWuyajiushu/js/hooks.min.map
LiexinWuyajiushu/js/reader.js
LiexinWuyajiushu/js/reader.js.map
LiexinWuyajiushu/js/reader.min.js
LiexinWuyajiushu/js/reader.min.map
LiexinWuyajiushu/js/hooks/__init__.py
LiexinWuyajiushu/js/hooks/extensions/__init__.py
LiexinWuyajiushu/js/hooks/extensions/highlight.js
LiexinWuyajiushu/js/libs/__init__.py
LiexinWuyajiushu/js/libs/jquery.min.js
LiexinWuyajiushu/js/libs/localforage.min.js
LiexinWuyajiushu/js/libs/screenfull.js
LiexinWuyajiushu/js/libs/screenfull.min.js
LiexinWuyajiushu/js/libs/zip.min.js
LiexinWuyajiushu/js/plugins/__init__.py
LiexinWuyajiushu/js/plugins/hypothesis.js
LiexinWuyajiushu/js/plugins/search.js
liexin_wuyajiushu-2022.10.11.0.dist-info/METADATA
liexin_wuyajiushu-2022.10.11.0.dist-info/WHEEL
liexin_wuyajiushu-2022.10.11.0.dist-info/entry_points.txt
liexin_wuyajiushu-2022.10.11.0.dist-info/top_level.txt
liexin_wuyajiushu-2022.10.11.0.dist-info/RECORD
